hass_splunk/__init__.py
hass_splunk-0.1.2.dist-info/LICENSE
hass_splunk-0.1.2.dist-info/METADATA
hass_splunk-0.1.2.dist-info/WHEEL
hass_splunk-0.1.2.dist-info/top_level.txt
hass_splunk-0.1.2.dist-info/RECORD
