Metadata-Version: 2.1
Name: hass-splunk
Version: 0.1.2
Summary: Async single threaded connector to Splunk HEC using an asyncio session
Home-page: https://github.com/Bre77/hass_splunk
Author: Brett Adams
Author-email: brett@ba.id.au
Classifier: Programming Language :: Python :: 3
Classifier: License :: OSI Approved :: MIT License
Classifier: Operating System :: OS Independent
Requires-Python: >=3.6
License-File: LICENSE
